DynamicStateMachine/DynamicStateMachine.py
DynamicStateMachine/State.py
DynamicStateMachine/States.py
DynamicStateMachine/__about__.py
DynamicStateMachine/__init__.py
dynamicstatemachine-0.0.3.dist-info/METADATA
dynamicstatemachine-0.0.3.dist-info/WHEEL
dynamicstatemachine-0.0.3.dist-info/licenses/LICENSE.txt
dynamicstatemachine-0.0.3.dist-info/RECORD
