Metadata-Version: 2.4
Name: DynamicStateMachine
Version: 0.0.3
Summary: A Python library for easily implementing state machines with complex conditionals
Project-URL: Documentation, https://github.com/smartycope/DynamicStateMachine#readme
Project-URL: Issues, https://github.com/smartycope/DynamicStateMachine/issues
Project-URL: Source, https://github.com/smartycope/DynamicStateMachine
Author-email: Copeland Carter <smartycope@gmail.com>
License-Expression: MIT
License-File: LICENSE.txt
Classifier: Development Status :: 4 - Beta
Classifier: Programming Language :: Python
Classifier: Programming Language :: Python :: 3.8
Classifier: Programming Language :: Python :: 3.9
Classifier: Programming Language :: Python :: 3.10
Classifier: Programming Language :: Python :: 3.11
Classifier: Programming Language :: Python :: 3.12
Classifier: Programming Language :: Python :: Implementation :: CPython
Classifier: Programming Language :: Python :: Implementation :: PyPy
Requires-Python: >=3.8
Requires-Dist: graphviz
